litestar_vite/__init__.py
litestar_vite/__metadata__.py
litestar_vite/cli.py
litestar_vite/commands.py
litestar_vite/deploy.py
litestar_vite/doctor.py
litestar_vite/exceptions.py
litestar_vite/executor.py
litestar_vite/html_transform.py
litestar_vite/loader.py
litestar_vite/py.typed
litestar_vite/utils.py
litestar_vite/codegen/__init__.py
litestar_vite/codegen/_export.py
litestar_vite/codegen/_inertia.py
litestar_vite/codegen/_openapi.py
litestar_vite/codegen/_routes.py
litestar_vite/codegen/_ts.py
litestar_vite/codegen/_utils.py
litestar_vite/config/__init__.py
litestar_vite/config/_constants.py
litestar_vite/config/_deploy.py
litestar_vite/config/_inertia.py
litestar_vite/config/_paths.py
litestar_vite/config/_runtime.py
litestar_vite/config/_spa.py
litestar_vite/config/_types.py
litestar_vite/handler/__init__.py
litestar_vite/handler/_app.py
litestar_vite/handler/_routing.py
litestar_vite/inertia/__init__.py
litestar_vite/inertia/_async_mixin.py
litestar_vite/inertia/_utils.py
litestar_vite/inertia/exception_handler.py
litestar_vite/inertia/helpers.py
litestar_vite/inertia/middleware.py
litestar_vite/inertia/plugin.py
litestar_vite/inertia/precognition.py
litestar_vite/inertia/request.py
litestar_vite/inertia/response.py
litestar_vite/inertia/types.py
litestar_vite/plugin/__init__.py
litestar_vite/plugin/_process.py
litestar_vite/plugin/_proxy.py
litestar_vite/plugin/_proxy_headers.py
litestar_vite/plugin/_static.py
litestar_vite/plugin/_utils.py
litestar_vite/scaffolding/__init__.py
litestar_vite/scaffolding/generator.py
litestar_vite/scaffolding/templates.py
litestar_vite/templates/__init__.py
litestar_vite/templates/addons/tailwindcss/tailwind.css.j2
litestar_vite/templates/angular/index.html.j2
litestar_vite/templates/angular/openapi-ts.config.ts.j2
litestar_vite/templates/angular/package.json.j2
litestar_vite/templates/angular/tsconfig.app.json.j2
litestar_vite/templates/angular/tsconfig.json.j2
litestar_vite/templates/angular/vite.config.ts.j2
litestar_vite-0.18.0.dist-info/METADATA
litestar_vite-0.18.0.dist-info/WHEEL
litestar_vite-0.18.0.dist-info/licenses/LICENSE
litestar_vite-0.18.0.dist-info/RECORD
