Metadata-Version: 2.4
Name: litestar-vite
Version: 0.18.0
Summary: Vite plugin for Litestar
Project-URL: Changelog, https://litestar-org.github.io/litestar-vite/latest/changelog
Project-URL: Discord, https://discord.gg/X3FJqy8d2j
Project-URL: Documentation, https://litestar-org.github.io/litestar-vite/latest/
Project-URL: Homepage, https://litestar-org.github.io/litestar-vite/latest/
Project-URL: Issue, https://github.com/litestar-org/litestar-vite/issues/
Project-URL: Source, https://github.com/litestar-org/litestar-vite
Author-email: Cody Fincher <cody.fincher@gmail.com>
License: MIT
License-File: LICENSE
Keywords: litestar,vite
Classifier: Environment :: Web Environment
Classifier: Intended Audience :: Developers
Classifier: Intended Audience :: System Administrators
Classifier: License :: OSI Approved :: MIT License
Classifier: Natural Language :: English
Classifier: Operating System :: OS Independent
Classifier: Programming Language :: Python
Classifier: Programming Language :: Python :: 3.10
Classifier: Programming Language :: Python :: 3.11
Classifier: Programming Language :: Python :: 3.12
Classifier: Programming Language :: Python :: 3.13
Classifier: Programming Language :: Python :: 3.14
Classifier: Topic :: Database
Classifier: Topic :: Database :: Database Engines/Servers
Classifier: Topic :: Software Development
Classifier: Typing :: Typed
Requires-Python: >=3.10
Requires-Dist: httpx>=0.24.1
Requires-Dist: litestar>=2.7.0
Requires-Dist: typing-extensions
Requires-Dist: websockets>=12.0
Provides-Extra: http2
Requires-Dist: h2>=4.0.0; extra == 'http2'
Provides-Extra: jinja
Requires-Dist: jinja2; extra == 'jinja'
Provides-Extra: nodeenv
Requires-Dist: nodeenv; extra == 'nodeenv'
